zwpy/__init__.py
zwpy-1.0.2.dist-info/LICENSE
zwpy-1.0.2.dist-info/METADATA
zwpy-1.0.2.dist-info/WHEEL
zwpy-1.0.2.dist-info/top_level.txt
zwpy-1.0.2.dist-info/RECORD
